multiocular/__init__.py
multiocular-0.1.0.dist-info/METADATA
multiocular-0.1.0.dist-info/WHEEL
multiocular-0.1.0.dist-info/top_level.txt
multiocular-0.1.0.dist-info/RECORD
