Metadata-Version: 2.4
Name: multiocular
Version: 0.1.0
Summary: A very simple helper library for keeping track of locations in tokenized text.
Requires-Python: >=3.12
Requires-Dist: jinja2>=3.1.6
Requires-Dist: transformers>=4.52.4
